{
	"name": "Friends",
	"source": "XPHB",
	"page": 277,
	"level": 0,
	"school": "E",
	"time": [
		{
			"number": 1,
			"unit": "action"
		}
	],
	"range": {
		"type": "point",
		"distance": {
			"type": "feet",
			"amount": 10
		}
	},
	"components": {
		"s": true,
		"m": "some makeup"
	},
	"duration": [
		{
			"type": "timed",
			"duration": {
				"type": "minute",
				"amount": 1
			},
			"concentration": true
		}
	],
	"entries": [
		"You magically emanate a sense of friendship toward one creature you can see within range. The target must succeed on a Wisdom saving throw or have the {@condition Charmed|XPHB} condition for the duration. The target succeeds automatically if it isn't a Humanoid, if you're fighting it, or if you have cast this spell on it within the past 24 hours.",
		"The spell ends early if the target takes damage or if you make an attack roll, deal damage, or force anyone to make a saving throw. When the spell ends, the target knows it was {@condition Charmed|XPHB} by you."
	],
	"conditionInflict": [
		"charmed"
	],
	"savingThrow": [
		"wisdom"
	],
	"affectsCreatureType": [
		"humanoid"
	],
	"areaTags": [
		"ST"
	],
	"classes": {
		"fromClassList": [
			{
				"name": "Bard",
				"source": "XPHB"
			},
			{
				"name": "Sorcerer",
				"source": "XPHB"
			},
			{
				"name": "Warlock",
				"source": "XPHB"
			},
			{
				"name": "Wizard",
				"source": "XPHB"
			}
		],
		"fromSubclass": [
			{
				"class": {
					"name": "Bard",
					"source": "XPHB"
				},
				"subclass": {
					"name": "College of Lore",
					"shortName": "Lore",
					"source": "XPHB"
				}
			},
			{
				"class": {
					"name": "Cleric",
					"source": "XPHB"
				},
				"subclass": {
					"name": "Arcana Domain",
					"shortName": "Arcana",
					"source": "SCAG"
				}
			},
			{
				"class": {
					"name": "Fighter",
					"source": "XPHB"
				},
				"subclass": {
					"name": "Eldritch Knight",
					"shortName": "Eldritch Knight",
					"source": "XPHB"
				}
			},
			{
				"class": {
					"name": "Rogue",
					"source": "XPHB"
				},
				"subclass": {
					"name": "Arcane Trickster",
					"shortName": "Arcane Trickster",
					"source": "XPHB"
				}
			},
			{
				"class": {
					"name": "Cleric",
					"source": "PHB"
				},
				"subclass": {
					"name": "Arcana Domain",
					"shortName": "Arcana",
					"source": "SCAG"
				}
			},
			{
				"class": {
					"name": "Fighter",
					"source": "PHB"
				},
				"subclass": {
					"name": "Eldritch Knight",
					"shortName": "Eldritch Knight",
					"source": "PHB"
				}
			},
			{
				"class": {
					"name": "Rogue",
					"source": "PHB"
				},
				"subclass": {
					"name": "Arcane Trickster",
					"shortName": "Arcane Trickster",
					"source": "PHB"
				}
			}
		]
	},
	"races": [
		{
			"name": "Elf (High)",
			"source": "PHB",
			"baseName": "Elf",
			"baseSource": "PHB"
		},
		{
			"name": "Elf",
			"source": "XPHB"
		},
		{
			"name": "Half-Elf (Variant; Moon Elf or Sun Elf Descent)",
			"source": "SCAG",
			"baseName": "Half-Elf",
			"baseSource": "PHB"
		},
		{
			"name": "Khoravar",
			"source": "EFA"
		},
		{
			"name": "Kobold",
			"source": "MPMM"
		},
		{
			"name": "Merfolk (Ixalan; Blue)",
			"source": "PSX",
			"baseName": "Merfolk",
			"baseSource": "PSZ"
		},
		{
			"name": "Siren",
			"source": "PSX"
		},
		{
			"name": "Merfolk (Zendikar; Cosi Creed)",
			"source": "PSZ",
			"baseName": "Merfolk",
			"baseSource": "PSZ"
		},
		{
			"name": "Merfolk (Zendikar; Ula Creed)",
			"source": "PSZ",
			"baseName": "Merfolk",
			"baseSource": "PSZ"
		},
		{
			"name": "Tiefling (Fierna)",
			"source": "MTF",
			"baseName": "Tiefling",
			"baseSource": "PHB"
		}
	],
	"optionalfeatures": [
		{
			"name": "Pact of the Tome",
			"source": "PHB",
			"featureType": [
				"PB"
			]
		},
		{
			"name": "Pact of the Tome",
			"source": "XPHB",
			"featureType": [
				"EI"
			]
		}
	],
	"backgrounds": [
		{
			"name": "Azorius Functionary",
			"source": "GGR"
		},
		{
			"name": "Orzhov Representative",
			"source": "GGR"
		},
		{
			"name": "Selesnya Initiate",
			"source": "GGR"
		}
	],
	"feats": [
		{
			"name": "Aberrant Dragonmark",
			"source": "EFA"
		},
		{
			"name": "Aberrant Dragonmark",
			"source": "ERLW"
		},
		{
			"name": "Cold Caster",
			"source": "FRHoF"
		},
		{
			"name": "Initiate of High Sorcery",
			"source": "DSotDQ"
		},
		{
			"name": "Magic Initiate",
			"source": "PHB"
		},
		{
			"name": "Magic Initiate",
			"source": "XPHB"
		}
	]
}